pyspv1/__init__.py
pyspv1/checkpathmodule.py
pyspv1/commandbasespv1.py
pyspv1/serialcommspv1.py
pyspv1/spsc.py
pyspv1/spv1.py
pyspv1/spv1dll.py
pyspv1/test.py
pyspv1-1.0.2.dist-info/METADATA
pyspv1-1.0.2.dist-info/WHEEL
pyspv1-1.0.2.dist-info/entry_points.txt
pyspv1-1.0.2.dist-info/top_level.txt
pyspv1-1.0.2.dist-info/RECORD
