Metadata-Version: 2.1
Name: pyspv1
Version: 1.0.2
Summary: SonMicro Standart Protocol V1(spv1) interface module.
Home-page: http://www.sonmicro.com/
Author: SonMicro Electronics
Author-email: info@sonmicro.com
License: MIT
Requires-Dist: pyserial
